{
  "schemaVersion": 1,
  "id": "${mod_id}",
  "version": "${mod_version}",
  "name": "${mod_name}",
  "authors": [
    "${mod_authors}"
  ],
  "contact": {
    "homepage": "https://www.curseforge.com/minecraft/mc-mods/notenoughrecipebook",
    "sources": ""
  },
  "license": "MIT",
  "environment": "*",
  "entrypoints": {
    "main": [
      "it.hurts.sskirillss.yagm.fabric.YAGMFabric"
    ],
    "client": [
      "it.hurts.sskirillss.yagm.fabric.client.YAGMFabricClient"
    ]
  },
  "mixins": [
    "yagm.mixins.json",
    "yagm-common.mixins.json"
  ],
  "depends": {
    "fabric": "*",
    "minecraft": ">=1.21.1"
  },
  "suggests": {
    "accessories": "*"
  }
}